lambda_dynamo_lock/__init__.py
lambda_dynamo_lock/lambda_dynamo_lock.py
lambda_dynamo_lock-0.1.3.dist-info/LICENSE
lambda_dynamo_lock-0.1.3.dist-info/METADATA
lambda_dynamo_lock-0.1.3.dist-info/WHEEL
lambda_dynamo_lock-0.1.3.dist-info/top_level.txt
lambda_dynamo_lock-0.1.3.dist-info/RECORD
