Metadata-Version: 2.1
Name: lambda-dynamo-lock
Version: 0.1.3
Summary: A utility for atomic DynamoDB operations in AWS Lambda functions
Home-page: https://github.com/jdaarevalo/lambda_dynamo_lock
Author: Jose David Arevalo
Author-email: jdaarevalo@gmail.com
Classifier: Programming Language :: Python :: 3
Classifier: License :: OSI Approved :: MIT License
Classifier: Operating System :: OS Independent
License-File: LICENSE
Requires-Dist: boto3
